openvariant/__init__.py
openvariant/annotation/__init__.py
openvariant/annotation/annotation.py
openvariant/annotation/builder.py
openvariant/annotation/config_annotation.py
openvariant/annotation/process.py
openvariant/commands/__init__.py
openvariant/commands/openvar.py
openvariant/find_files/__init__.py
openvariant/find_files/find_files.py
openvariant/plugins/__init__.py
openvariant/plugins/context.py
openvariant/plugins/plugin.py
openvariant/plugins/alteration_type/__init__.py
openvariant/plugins/alteration_type/alteration_type.py
openvariant/plugins/get_AF/__init__.py
openvariant/plugins/get_AF/get_AF.py
openvariant/plugins/liftover/__init__.py
openvariant/plugins/liftover/liftover.py
openvariant/tasks/__init__.py
openvariant/tasks/cat.py
openvariant/tasks/count.py
openvariant/tasks/groupby.py
openvariant/tasks/plugin.py
openvariant/utils/__init__.py
openvariant/utils/utils.py
openvariant/variant/__init__.py
openvariant/variant/variant.py
openvariant/variant/where.py
open_variant-1.1.0.dist-info/METADATA
open_variant-1.1.0.dist-info/WHEEL
open_variant-1.1.0.dist-info/entry_points.txt
open_variant-1.1.0.dist-info/licenses/LICENSE
open_variant-1.1.0.dist-info/RECORD
