Metadata-Version: 2.4
Name: open-variant
Version: 1.1.0
Summary: OpenVariant provides different functionalities to read, parse and operate different multiple input file formats, being able to customize the output.
Project-URL: Homepage, https://github.com/bbglab/openvariant
Project-URL: Documentation, https://openvariant.readthedocs.io/
Project-URL: Repository, https://github.com/bbglab/openvariant
Project-URL: Issues, https://github.com/bbglab/openvariant/issues
Author-email: "BBGLab (Barcelona Biomedical Genomics Lab)" <bbglab@irbbarcelona.org>
License: BSD 3-Clause License
License-File: LICENSE
Keywords: bbglab,bioinformatics,openvar,openvariant
Requires-Python: >=3.10
Requires-Dist: appdirs==1.4.4
Requires-Dist: click==8.1.3
Requires-Dist: pyliftover==0.4.1
Requires-Dist: pyyaml==6.0.1
Requires-Dist: tqdm==4.66.3
Provides-Extra: docs
Requires-Dist: alabaster==0.7.12; extra == 'docs'
Requires-Dist: asttokens==2.0.5; extra == 'docs'
Requires-Dist: attrs==22.1.0; extra == 'docs'
Requires-Dist: babel==2.10.3; extra == 'docs'
Requires-Dist: backcall==0.2.0; extra == 'docs'
Requires-Dist: beautifulsoup4==4.11.1; extra == 'docs'
Requires-Dist: bleach==5.0.1; extra == 'docs'
Requires-Dist: charset-normalizer==2.1.0; extra == 'docs'
Requires-Dist: click==8.1.3; extra == 'docs'
Requires-Dist: decorator==5.1.1; extra == 'docs'
Requires-Dist: defusedxml==0.7.1; extra == 'docs'
Requires-Dist: docutils==0.17.1; extra == 'docs'
Requires-Dist: entrypoints==0.4; extra == 'docs'
Requires-Dist: executing==0.9.1; extra == 'docs'
Requires-Dist: fastjsonschema==2.16.1; extra == 'docs'
Requires-Dist: idna==3.7; extra == 'docs'
Requires-Dist: imagesize==1.4.1; extra == 'docs'
Requires-Dist: ipython>=8.18.0; extra == 'docs'
Requires-Dist: jedi==0.18.1; extra == 'docs'
Requires-Dist: jinja2==3.1.4; extra == 'docs'
Requires-Dist: jsonschema==4.8.0; extra == 'docs'
Requires-Dist: jupyter-client==7.3.4; extra == 'docs'
Requires-Dist: jupyter-core==4.11.2; extra == 'docs'
Requires-Dist: jupyterlab-pygments==0.2.2; extra == 'docs'
Requires-Dist: markupsafe==2.1.1; extra == 'docs'
Requires-Dist: matplotlib-inline==0.1.3; extra == 'docs'
Requires-Dist: mistune==2.0.3; extra == 'docs'
Requires-Dist: nbclient==0.6.6; extra == 'docs'
Requires-Dist: nbconvert==7.0.0rc0; extra == 'docs'
Requires-Dist: nbformat==5.4.0; extra == 'docs'
Requires-Dist: nbsphinx==0.8.9; extra == 'docs'
Requires-Dist: nest-asyncio==1.5.5; extra == 'docs'
Requires-Dist: packaging==21.3; extra == 'docs'
Requires-Dist: pandocfilters==1.5.0; extra == 'docs'
Requires-Dist: parso==0.8.3; extra == 'docs'
Requires-Dist: pexpect==4.8.0; extra == 'docs'
Requires-Dist: pickleshare==0.7.5; extra == 'docs'
Requires-Dist: prompt-toolkit==3.0.30; extra == 'docs'
Requires-Dist: ptyprocess==0.7.0; extra == 'docs'
Requires-Dist: pure-eval==0.2.2; extra == 'docs'
Requires-Dist: pydata-sphinx-theme==0.8.1; extra == 'docs'
Requires-Dist: pygments==2.15.0; extra == 'docs'
Requires-Dist: pyparsing==3.0.9; extra == 'docs'
Requires-Dist: pyrsistent==0.18.1; extra == 'docs'
Requires-Dist: python-dateutil==2.8.2; extra == 'docs'
Requires-Dist: pytz==2022.1; extra == 'docs'
Requires-Dist: pyyaml==6.0.1; extra == 'docs'
Requires-Dist: pyzmq==26.2.0; extra == 'docs'
Requires-Dist: requests==2.32.2; extra == 'docs'
Requires-Dist: ruamel-yaml==0.16.13; extra == 'docs'
Requires-Dist: setuptools>=58.2.0; extra == 'docs'
Requires-Dist: six==1.16.0; extra == 'docs'
Requires-Dist: snowballstemmer==2.2.0; extra == 'docs'
Requires-Dist: soupsieve==2.3.2.post1; extra == 'docs'
Requires-Dist: sphinx-copybutton==0.5.0; extra == 'docs'
Requires-Dist: sphinx-gallery==0.10.1; extra == 'docs'
Requires-Dist: sphinx-panels==0.6.0; extra == 'docs'
Requires-Dist: sphinx==4.5.0; extra == 'docs'
Requires-Dist: sphinxcontrib-applehelp==1.0.2; extra == 'docs'
Requires-Dist: sphinxcontrib-autoyaml==1.0.0; extra == 'docs'
Requires-Dist: sphinxcontrib-bibtex==2.6.3; extra == 'docs'
Requires-Dist: sphinxcontrib-devhelp==1.0.2; extra == 'docs'
Requires-Dist: sphinxcontrib-htmlhelp==2.0.0; extra == 'docs'
Requires-Dist: sphinxcontrib-jsmath==1.0.1; extra == 'docs'
Requires-Dist: sphinxcontrib-qthelp==1.0.3; extra == 'docs'
Requires-Dist: sphinxcontrib-serializinghtml==1.1.5; extra == 'docs'
Requires-Dist: stack-data==0.3.0; extra == 'docs'
Requires-Dist: tinycss2==1.1.1; extra == 'docs'
Requires-Dist: tornado==6.4.2; extra == 'docs'
Requires-Dist: tqdm==4.66.3; extra == 'docs'
Requires-Dist: traitlets==5.3.0; extra == 'docs'
Requires-Dist: urllib3==1.26.19; extra == 'docs'
Requires-Dist: wcwidth==0.2.5; extra == 'docs'
Requires-Dist: webencodings==0.5.1; extra == 'docs'
Provides-Extra: linting
Requires-Dist: flake8>=7.1.1; extra == 'linting'
Requires-Dist: ruff>=0.8.3; extra == 'linting'
Provides-Extra: tests
Requires-Dist: coverage>=7.6.9; extra == 'tests'
Requires-Dist: pytest-cov>=6.0.0; extra == 'tests'
Requires-Dist: pytest>=8.3.4; extra == 'tests'
